PySXO/__init__.py
PySXO/exceptions.py
PySXO/workflow.py
PySXO/workflows.py
PySXO/core/__init__.py
PySXO/core/base.py
PySXO/core/decorators.py
PySXO/core/enum.py
PySXO/core/request_handler.py
PySXO/enum/__init__.py
PySXO/enum/instance_state.py
PySXO/instances/__init__.py
PySXO/instances/get.py
PySXO/instances/list.py
PySXO-0.0.17.dist-info/METADATA
PySXO-0.0.17.dist-info/WHEEL
PySXO-0.0.17.dist-info/top_level.txt
PySXO-0.0.17.dist-info/RECORD
